fbespice/__init__.py
fbespice/netlist.py
fbespice/results/__init__.py
fbespice/results/raw.py
fbespice/results/xyce.py
fbespice/run/__init__.py
fbespice/run/base.py
fbespice/run/ngspice.py
fbespice/run/xyce.py
fbespice-0.8.dist-info/METADATA
fbespice-0.8.dist-info/WHEEL
fbespice-0.8.dist-info/RECORD
