Metadata-Version: 2.3
Name: fbespice
Version: 0.8
Summary: Python library for inteaction with SPICE-like simulators
Project-URL: Homepage, https://gitlab.com/fbengineering/fbespice
Project-URL: Documentation, https://fbengineering.gitlab.io/fbespice
Author-email: Federico Beffa <beffa@fbengineering.ch>
Keywords: CAD,electronics,netlist,simulation,spice,xyce
Classifier: License :: OSI Approved :: GNU General Public License v3 or later (GPLv3+)
Classifier: Operating System :: OS Independent
Classifier: Programming Language :: Python :: 3
Requires-Python: >=3.10
Requires-Dist: numpy>=1.26
Requires-Dist: pandas>=2.0.0
Provides-Extra: dev
Requires-Dist: pytest; extra == 'dev'
